odoo/addons/ssi_helpdesk_project/README.rst
odoo/addons/ssi_helpdesk_project/__init__.py
odoo/addons/ssi_helpdesk_project/__manifest__.py
odoo/addons/ssi_helpdesk_project/models/__init__.py
odoo/addons/ssi_helpdesk_project/models/helpdesk_ticket.py
odoo/addons/ssi_helpdesk_project/models/helpdesk_type.py
odoo/addons/ssi_helpdesk_project/models/helpdesk_type_task.py
odoo/addons/ssi_helpdesk_project/models/project_task.py
odoo/addons/ssi_helpdesk_project/security/ir.model.access.csv
odoo/addons/ssi_helpdesk_project/static/description/icon.png
odoo/addons/ssi_helpdesk_project/views/helpdesk_ticket_views.xml
odoo/addons/ssi_helpdesk_project/views/helpdesk_type_views.xml
odoo/addons/ssi_helpdesk_project/views/project_task_views.xml
odoo/addons/ssi_helpdesk_project/wizards/__init__.py
odoo/addons/ssi_helpdesk_project/wizards/create_sucessor_task.py
odoo/addons/ssi_helpdesk_project/wizards/create_ticket_from_communication.py
odoo/addons/ssi_helpdesk_project/wizards/split_helpdesk_ticket.py
odoo14_addon_ssi_helpdesk_project-14.0.3.1.0.dist-info/METADATA
odoo14_addon_ssi_helpdesk_project-14.0.3.1.0.dist-info/WHEEL
odoo14_addon_ssi_helpdesk_project-14.0.3.1.0.dist-info/top_level.txt
odoo14_addon_ssi_helpdesk_project-14.0.3.1.0.dist-info/RECORD
